GithubAIPy/__init__.py
GithubAIPy/api.py
GithubAIPy-0.1.1.dist-info/METADATA
GithubAIPy-0.1.1.dist-info/WHEEL
GithubAIPy-0.1.1.dist-info/top_level.txt
GithubAIPy-0.1.1.dist-info/RECORD
