Metadata-Version: 2.1
Name: GithubAIPy
Version: 0.1.1
Summary: A Python package to interact with GitHub AI models.
Home-page: https://github.com/Ramona-Flower/GithubAIPy
Author: Ramona-Flower
Classifier: Programming Language :: Python :: 3
Classifier: License :: OSI Approved :: MIT License
Classifier: Operating System :: OS Independent
Requires-Python: >=3.6
Requires-Dist: requests >=2.31.0
